aanchal_task/Task1.py
aanchal_task/Task2and3.py
aanchal_task/__init__.py
aanchal_task/data.ipynb
aanchal_task-0.1.0.dist-info/WHEEL
aanchal_task-0.1.0.dist-info/METADATA
aanchal_task-0.1.0.dist-info/RECORD
