Metadata-Version: 2.1
Name: aanchal-task
Version: 0.1.0
Summary: 
Author: GNMML
Author-email: alihan.keleser@bayer.com
Requires-Python: >=3.8,<4.0
Classifier: Programming Language :: Python :: 3
Classifier: Programming Language :: Python :: 3.10
Classifier: Programming Language :: Python :: 3.8
Classifier: Programming Language :: Python :: 3.9
Requires-Dist: pandas (>=1.4.3,<2.0.0)
